kahi_staff_udea_affiliations/Kahi_staff_udea_affiliations.py
kahi_staff_udea_affiliations/__init__.py
kahi_staff_udea_affiliations/_version.py
Kahi_staff_udea_affiliations-0.1.1b0.dist-info/LICENSE
Kahi_staff_udea_affiliations-0.1.1b0.dist-info/METADATA
Kahi_staff_udea_affiliations-0.1.1b0.dist-info/WHEEL
Kahi_staff_udea_affiliations-0.1.1b0.dist-info/top_level.txt
Kahi_staff_udea_affiliations-0.1.1b0.dist-info/RECORD
